sphinxemoji/__init__.py
sphinxemoji/codes.json
sphinxemoji/sphinxemoji.py
sphinxemoji/twemoji.css
sphinxemoji/twemoji.js
sphinxemoji/utils.py
sphinxemoji-0.3.2.dist-info/licenses/LICENSE
sphinxemoji-0.3.2.dist-info/METADATA
sphinxemoji-0.3.2.dist-info/WHEEL
sphinxemoji-0.3.2.dist-info/top_level.txt
sphinxemoji-0.3.2.dist-info/RECORD
